dsert/__init__.py
dsert-0.1.3.dist-info/DESCRIPTION.rst
dsert-0.1.3.dist-info/METADATA
dsert-0.1.3.dist-info/RECORD
dsert-0.1.3.dist-info/WHEEL
dsert-0.1.3.dist-info/metadata.json
dsert-0.1.3.dist-info/top_level.txt
