Metadata-Version: 2.0
Name: dsert
Version: 0.1.3
Summary: Test all fields of a python dictionary
Home-page: https://github.com/paxos-bankchain/dsert
Author: Paxos Trust Company, LLC
Author-email: pypi@paxos.com
License: MIT
Platform: UNKNOWN
Classifier: Topic :: Software Development :: Testing
Classifier: License :: OSI Approved :: MIT License
Classifier: Programming Language :: Python :: 2.7
Classifier: Programming Language :: Python :: 3.2
Classifier: Programming Language :: Python :: 3.3
Classifier: Programming Language :: Python :: 3.4
Classifier: Programming Language :: Python :: 3.5
Classifier: Programming Language :: Python :: 3.6
